{
  "doc_id": "gh-024",
  "source_type": "github_issue",
  "title": "[performance] API & Webhooks: reported by Acme Robotics",
  "created_at": "2025-12-02",
  "text": "Issue #1023 \u2014 performance in API & Webhooks\nState: closed\nLabels: performance, area:api-&-webhooks\n\nOriginating customer report: Acme Robotics.\nSteps to reproduce documented. Fixed in release 7.4 and verified.",
  "metadata": {
    "product_area": "API & Webhooks",
    "state": "closed",
    "kind": "performance",
    "customer": "Acme Robotics",
    "fixed": true
  }
}