{
  "doc_id": "meeting-015",
  "source_type": "meeting_notes",
  "title": "Product sync \u2014 2026-05-09",
  "created_at": "2026-05-09",
  "text": "# Weekly Product Sync \u2014 2026-05-09\nAttendees: PM, Eng Lead, CS Lead\n\n## Discussion\n- Acme Robotics escalated API & Webhooks problems again; churn risk flagged.\n- Repeated ask for 'Granular notification controls' across accounts.\n- Eng notes API & Webhooks generates the most support load this month.\n\n## Action items\n- [ ] Evaluate 'Granular notification controls' for roadmap.\n- [ ] Investigate API & Webhooks performance regressions.\n- [ ] Follow up with Acme Robotics.",
  "metadata": {
    "product_area": "API & Webhooks",
    "feature": "Granular notification controls",
    "customer": "Acme Robotics"
  }
}