{
  "doc_id": "ticket-012",
  "source_type": "support_ticket",
  "title": "[URGENT] Dashboards issue \u2014 Sunrise Bank",
  "created_at": "2025-08-10",
  "text": "Customer: Sunrise Bank (Enterprise)\nProduct area: Dashboards\nPriority: urgent\nStatus: open\n\nDescription: The dashboard takes 12 seconds to load when I have more than 10000 widgets. It's unusable for our morning standup.\n\nSupport notes: Reproduced on our side. Escalated to engineering.",
  "metadata": {
    "customer": "Sunrise Bank",
    "tier": "Enterprise",
    "product_area": "Dashboards",
    "status": "open",
    "priority": "urgent",
    "sentiment": "negative"
  }
}