{
  "doc_id": "ticket-050",
  "source_type": "support_ticket",
  "title": "[MEDIUM] API & Webhooks issue \u2014 Ferns & Co",
  "created_at": "2026-02-09",
  "text": "Customer: Ferns & Co (SMB)\nProduct area: API & Webhooks\nPriority: medium\nStatus: in_progress\n\nDescription: Our webhooks silently fail and there are no retries, so we miss events constantly.\n\nSupport notes: Reproduced on our side. Added to backlog.",
  "metadata": {
    "customer": "Ferns & Co",
    "tier": "SMB",
    "product_area": "API & Webhooks",
    "status": "in_progress",
    "priority": "medium",
    "sentiment": "negative"
  }
}